ark_server/__init__.py
ark_server/__main__.py
ark_server_certic-0.0.14.dist-info/METADATA
ark_server_certic-0.0.14.dist-info/WHEEL
ark_server_certic-0.0.14.dist-info/entry_points.txt
ark_server_certic-0.0.14.dist-info/RECORD
